<wdkModel>

<querySet name="DynSpanId" queryType="id">


 <!--++++++++++++++++++++++++++++++++++++++++++++++++++++++++++++++-->
  <!-- Location -->
  <!--++++++++++++++++++++++++++++++++++++++++++++++++++++++++++++++-->



   <sqlQuery name="DynSpansByLocation"
              isCacheable="true" doNotTest="true">
        <paramRef ref="sharedParams.sequenceId"/>
        <paramRef ref="sharedParams.start_point"/>
        <paramRef ref="sharedParams.end_point"/>
        <column name="project_id"/>
        <column name="source_id" width="50"/>
        <sql>
            <![CDATA[
            SELECT 
              $$sequenceId$$ || ':' || $$start_point$$  || '-' || $$end_point$$ || ':+' 
                  as source_id,  '@PROJECT_ID@' as project_id
           FROM dual

           ]]>
       </sql>
 </sqlQuery>

<!--++++++++++++++++++++++++++++++++++++++++++++++++++++++++++++++-->
  <!-- Motif search -->
  <!--++++++++++++++++++++++++++++++++++++++++++++++++++++++++++++++-->

    <processQuery name="DynSpansByMotifSearch" excludeProjects="EuPathDB"
             processName="org.apidb.apicomplexa.wsfplugin.dnamotifsearch.DnaMotifSearchPlugin">
       <paramRef ref="sharedParams.motif_expression"/>
       <paramRef ref="genomicSimilarityParams.motif_organism" quote="false" />
       <wsColumn name="source_id" width="50" wsName="DynSpanID"/>
       <wsColumn name="project_id" width="32" wsName="ProjectId"/>
       <wsColumn name="Locations" width="3999"/>
       <wsColumn name="MatchCount" width="15"/>
       <wsColumn name="Sequence" width="3999"/>
    </processQuery>


</querySet>

</wdkModel>

